{"mapnearby":{"path":"\/home\/group\/public_html\/wp-demo\/directorybox\/rtl\/wp-content\/uploads\/cs-icons-manager\/mapnearby","url":"http:\/\/directorybox.chimpgroup.com\/rtl\/wp-content\/uploads\/cs-icons-manager\/mapnearby","status":"on"},"custom-fileds":{"path":"\/home\/group\/public_html\/wp-demo\/directorybox\/rtl\/wp-content\/uploads\/cs-icons-manager\/custom-fileds","url":"http:\/\/directorybox.chimpgroup.com\/rtl\/wp-content\/uploads\/cs-icons-manager\/custom-fileds","status":"on"},"listingtype":{"path":"\/home\/group\/public_html\/wp-demo\/directorybox\/rtl\/wp-content\/uploads\/cs-icons-manager\/listingtype","url":"http:\/\/directorybox.chimpgroup.com\/rtl\/wp-content\/uploads\/cs-icons-manager\/listingtype","status":"on"},"icon_category":{"path":"\/home\/group\/public_html\/wp-demo\/directorybox\/rtl\/wp-content\/uploads\/cs-icons-manager\/icon_category","url":"http:\/\/directorybox.chimpgroup.com\/rtl\/wp-content\/uploads\/cs-icons-manager\/icon_category","status":"on"},"default":{"path":"\/home\/group\/public_html\/wp-demo\/directorybox\/rtl\/wp-content\/plugins\/cs-icons-manager\/assets\/default","url":"http:\/\/directorybox.chimpgroup.com\/rtl\/wp-content\/plugins\/cs-icons-manager\/assets\/default","status":"on"}}